liquipediapy/__init__.py
liquipediapy/counterstrike.py
liquipediapy/dota.py
liquipediapy/exceptions.py
liquipediapy/liquipediapy.py
liquipediapy/counterstrike_modules/__init__.py
liquipediapy/counterstrike_modules/player.py
liquipediapy/counterstrike_modules/team.py
liquipediapy/dota_modules/__init__.py
liquipediapy/dota_modules/player.py
liquipediapy/dota_modules/pro_circuit.py
liquipediapy/dota_modules/team.py
liquipediapy2-2.0.0.dist-info/LICENSE
liquipediapy2-2.0.0.dist-info/METADATA
liquipediapy2-2.0.0.dist-info/WHEEL
liquipediapy2-2.0.0.dist-info/top_level.txt
liquipediapy2-2.0.0.dist-info/RECORD
